DataScienceIpythonNotebook20160913/README.md
DataScienceIpythonNotebook20160913/__init__.py
DataScienceIpythonNotebook20160913/__main__.py
DataScienceIpythonNotebook20160913/file.epub
DataScienceIpythonNotebook20160913/index.html
DataScienceIpythonNotebook20160913/css/__init__.py
DataScienceIpythonNotebook20160913/css/annotations.css
DataScienceIpythonNotebook20160913/css/main.css
DataScienceIpythonNotebook20160913/css/normalize.css
DataScienceIpythonNotebook20160913/css/popup.css
DataScienceIpythonNotebook20160913/font/__init__.py
DataScienceIpythonNotebook20160913/font/fontello.eot
DataScienceIpythonNotebook20160913/font/fontello.svg
DataScienceIpythonNotebook20160913/font/fontello.ttf
DataScienceIpythonNotebook20160913/font/fontello.woff
DataScienceIpythonNotebook20160913/img/__init__.py
DataScienceIpythonNotebook20160913/img/annotator-glyph-sprite.png
DataScienceIpythonNotebook20160913/img/annotator-icon-sprite.png
DataScienceIpythonNotebook20160913/img/apple-touch-icon.png
DataScienceIpythonNotebook20160913/img/cancelfullscreen.png
DataScienceIpythonNotebook20160913/img/close.png
DataScienceIpythonNotebook20160913/img/fullscreen.png
DataScienceIpythonNotebook20160913/img/loader.gif
DataScienceIpythonNotebook20160913/img/menu-icon.png
DataScienceIpythonNotebook20160913/img/save.png
DataScienceIpythonNotebook20160913/img/saved.png
DataScienceIpythonNotebook20160913/img/settings-s.png
DataScienceIpythonNotebook20160913/img/settings.png
DataScienceIpythonNotebook20160913/img/star.png
DataScienceIpythonNotebook20160913/js/__init__.py
DataScienceIpythonNotebook20160913/js/epub.js
DataScienceIpythonNotebook20160913/js/epub.min.js
DataScienceIpythonNotebook20160913/js/epub.min.map
DataScienceIpythonNotebook20160913/js/hooks.min.js
DataScienceIpythonNotebook20160913/js/hooks.min.map
DataScienceIpythonNotebook20160913/js/reader.js
DataScienceIpythonNotebook20160913/js/reader.js.map
DataScienceIpythonNotebook20160913/js/reader.min.js
data_science_ipython_notebook_20160913-2024.3.1.0.dist-info/METADATA
data_science_ipython_notebook_20160913-2024.3.1.0.dist-info/WHEEL
data_science_ipython_notebook_20160913-2024.3.1.0.dist-info/entry_points.txt
data_science_ipython_notebook_20160913-2024.3.1.0.dist-info/top_level.txt
data_science_ipython_notebook_20160913-2024.3.1.0.dist-info/RECORD
